XStatic_JS_Yaml-3.8.1.0-py2.7-nspkg.pth
XStatic_JS_Yaml-3.8.1.0.dist-info/METADATA
XStatic_JS_Yaml-3.8.1.0.dist-info/RECORD
XStatic_JS_Yaml-3.8.1.0.dist-info/WHEEL
XStatic_JS_Yaml-3.8.1.0.dist-info/namespace_packages.txt
XStatic_JS_Yaml-3.8.1.0.dist-info/top_level.txt
xstatic/pkg/js_yaml/__init__.py
xstatic/pkg/js_yaml/data/js-yaml.js
