Metadata-Version: 2.1
Name: XStatic-JS-Yaml
Version: 3.8.1.0
Summary: JS-Yaml 3.8.1 (XStatic packaging standard)
Home-page: https://github.com/nodeca/js-yaml
Maintainer: xinni.ge
Maintainer-email: xinni.ge@ntt.com
License: MIT
Keywords: js_yaml xstatic
Platform: any
